{
  "date": "2024-12-13",
  "items": [
    {
      "id": "pf-20260202-zealy-ffb02e80",
      "company_slug": "zealy",
      "company_name": "Zealy",
      "date_published": "2024-12-13T08:00:00.000Z",
      "date_ingested": "2026-02-02T18:08:41.143Z",
      "source_type": "news",
      "title": "Xenea: Pioneering Blockchain Innovation and Airdrop Opportunities - Binance",
      "url": "https://news.google.com/rss/articles/CBMiY0FVX3lxTE0wSmNWZGoyOTJHMDJqbTdINGJvaHRVcGZoNmZsTGpoazctcTU2RThLUy1XemxqRWZ1NzBrX2dzYlBVZ1dzcXNHM2NCZTdQZXZaRHE0a21IUmYwX0VmelRjVE05Zw?oc=5",
      "publisher": "Binance",
      "summary_short": "Xenea: Pioneering Blockchain Innovation and Airdrop Opportunities Binance",
      "image_url": null,
      "significance_score": 5,
      "sentiment": "neutral",
      "tags": []
    }
  ],
  "generated_at": "2026-02-02T18:09:12.159Z"
}