[
    {
        "month": "January 2026",
        "title": "Market Volatility, Institutional Momentum, Security Challenges",
        "filename": "blockwall-monthly-2026-01.html",
        "stories": 787,
        "bullish": 203,
        "bearish": 245,
        "thumbnail": "https://images.unsplash.com/photo-1611974789855-9c2a0a7236a3?w=800&h=400&fit=crop",
        "snippet": "January delivered volatile markets with $100B erased in a weekend crash. $2.5B in liquidations hit as Bitcoin fell to $77K. UAE-backed investor took 49% stake in Trump-linked crypto firm for $500M. Security breaches totaled $86M across 16 incidents."
    }
]